{"frames":[{"filename":"frame8","frame":{"x":24,"y":0,"w":14,"h":22},"rotated":false,"trimmed":false,"spriteSourceSize":{"x":0,"y":0,"w":14,"h":22},"sourceSize":{"w":14,"h":22}},{"filename":"frame9","frame":{"x":0,"y":0,"w":23,"h":27},"rotated":false,"trimmed":false,"spriteSourceSize":{"x":0,"y":0,"w":23,"h":27},"sourceSize":{"w":23,"h":27}},{"filename":"frame10","frame":{"x":39,"y":30,"w":25,"h":31},"rotated":false,"trimmed":false,"spriteSourceSize":{"x":0,"y":0,"w":25,"h":31},"sourceSize":{"w":25,"h":31}},{"filename":"frame11","frame":{"x":39,"y":0,"w":28,"h":29},"rotated":false,"trimmed":false,"spriteSourceSize":{"x":0,"y":0,"w":28,"h":29},"sourceSize":{"w":28,"h":29}},{"filename":"frame12","frame":{"x":33,"y":64,"w":31,"h":24},"rotated":false,"trimmed":false,"spriteSourceSize":{"x":0,"y":0,"w":31,"h":24},"sourceSize":{"w":31,"h":24}},{"filename":"frame13","frame":{"x":0,"y":64,"w":32,"h":27},"rotated":false,"trimmed":false,"spriteSourceSize":{"x":0,"y":0,"w":32,"h":27},"sourceSize":{"w":32,"h":27}},{"filename":"frame14","frame":{"x":0,"y":28,"w":36,"h":35},"rotated":false,"trimmed":false,"spriteSourceSize":{"x":0,"y":0,"w":36,"h":35},"sourceSize":{"w":36,"h":35}}],"meta":{"app":"http://www.leshylabs.com/apps/sstool/","version":"Leshy SpriteSheet Tool v0.8.1","size":{"w":67,"h":91},"scale":1}}